{
    "AX": {
        "error": 0.0562615519474732, 
        "fit": "average_SEM", 
        "value": -0.010556643645820271
    }, 
    "CDD": {
        "error": 0.00012516720205606196, 
        "fit": "average_SEM", 
        "value": 0.00010747303862849044
    }, 
    "H1": {
        "error": 0.12048147354951763, 
        "fit": "average_SEM", 
        "value": 0.05499985998748242
    }, 
    "H2": {
        "error": 0.10888917963903187, 
        "fit": "average_SEM", 
        "value": -0.17754137171691076
    }, 
    "L1": {
        "error": 0.26322021757673114, 
        "fit": "average_SEM", 
        "value": 0.04196208508995672
    }, 
    "L2": {
        "error": 0.16049790583275492, 
        "fit": "average_SEM", 
        "value": 0.01269340179860592
    }
}