{
    "Ar36": {
        "error": 0.0013863053139821712, 
        "fit": "linear", 
        "value": 0.0089428862862839329
    }, 
    "Ar37": {
        "error": 0.13393990297751091, 
        "fit": "linear", 
        "value": 0.081308901076339285
    }, 
    "Ar38": {
        "error": 0.32169378490426775, 
        "fit": "linear", 
        "value": 0.18144655325190914
    }, 
    "Ar39": {
        "error": 0.065216319742622791, 
        "fit": "linear", 
        "value": 9.6440568387715615
    }, 
    "Ar40": {
        "error": 0.56750491659093727, 
        "fit": "linear", 
        "value": 1782.9853452086786
    }, 
    "Ar41": {
        "error": 0.12248904139414378, 
        "fit": "average_SEM", 
        "value": -0.10558037283209463
    }
}